{"title":"GroupBanged.17.02.03.Two.Horny.Chicks.Get.Gang.Banged.Hardcor...","magnet":"magnet:?xt=urn:btih:0a2e3d4a482162b33d1c882248b8337f88406314&dn=GroupBanged.17.02.03.Two.Horny.Chicks.Get.Gang.Banged.Hardcor...&tr=udp%3A%2F%2Ftracker.leechers-paradise.org%3A6969&tr=udp%3A%2F%2Fzer0day.ch%3A1337&tr=udp%3A%2F%2Fopen.demonii.com%3A1337&tr=udp%3A%2F%2Ftracker.coppersurfer.tk%3A6969&tr=udp%3A%2F%2Fexodus.desync.com%3A6969","uploader":"juggs99","categoryP":"porn","categoryS":"hd___movies","size":"2897514417","seeders":"6","leechers":"19","description":"\nGroupBanged.17.02.03.Two.Horny.Chicks.Get.Gang.Banged.Hardcore.XXX.1080p.MP4-KTR \r\n\n\n[Format]:    MPEG-4\n[Duration]:    37mn 55s\n[Resolution]:  1 920 x 1 080 pixels\n[Display aspect ratio]:    16:9\n[Frame rate mode]:    Constant\n[Frame rate]:    25.000 fps\n\r\n\n#N1C -&gt; To avoid fakes, ALWAYS check that the torrent was added by NO1CARES\r\n\n\r\n\n\nHelp us by donating with Bitcoin: 1Pgwp16gmLHmPzgjJLxZnMw7YeqiUekUoe\r\n\nScreens...\r <a href=\"\nhttps://www.xxximagetpb.org/image/HplT8\" rel=\"nofollow\" target=\"_NEW\">\nhttps://www.xxximagetpb.org/image/HplT8</a>\r <a href=\"\nhttps://www.xxximagetpb.org/image/HpDrP\" rel=\"nofollow\" target=\"_NEW\">\nhttps://www.xxximagetpb.org/image/HpDrP</a>\r <a href=\"\nhttps://www.xxximagetpb.org/image/HpvR7\" rel=\"nofollow\" target=\"_NEW\">\nhttps://www.xxximagetpb.org/image/HpvR7</a>\r <a href=\"\nhttps://www.xxximagetpb.org/image/HpAWb\" rel=\"nofollow\" target=\"_NEW\">\nhttps://www.xxximagetpb.org/image/HpAWb</a>","last_updated":"2017-06-04T12:03:01.271Z","parsed":{"xt":"urn:btih:0a2e3d4a482162b33d1c882248b8337f88406314","dn":"GroupBanged.17.02.03.Two.Horny.Chicks.Get.Gang.Banged.Hardcor...","tr":["udp://exodus.desync.com:6969","udp://open.demonii.com:1337","udp://tracker.coppersurfer.tk:6969","udp://tracker.leechers-paradise.org:6969","udp://zer0day.ch:1337"],"infoHash":"0a2e3d4a482162b33d1c882248b8337f88406314","infoHashBuffer":{"type":"Buffer","data":[10,46,61,74,72,33,98,179,61,28,136,34,72,184,51,127,136,64,99,20]},"name":"GroupBanged.17.02.03.Two.Horny.Chicks.Get.Gang.Banged.Hardcor...","announce":["udp://exodus.desync.com:6969","udp://open.demonii.com:1337","udp://tracker.coppersurfer.tk:6969","udp://tracker.leechers-paradise.org:6969","udp://zer0day.ch:1337"],"urlList":[]}}