{"title":"Howard Stern Show OCT 30 2017 Mon","magnet":"magnet:?xt=urn:btih:1df8ad9fefbfdd6ac7ccbf653262179b6d91f851&dn=Howard+Stern+Show+OCT+30+2017+Mon&tr=udp%3A%2F%2Ftracker.leechers-paradise.org%3A6969&tr=udp%3A%2F%2Fzer0day.ch%3A1337&tr=udp%3A%2F%2Fopen.demonii.com%3A1337&tr=udp%3A%2F%2Ftracker.coppersurfer.tk%3A6969&tr=udp%3A%2F%2Fexodus.desync.com%3A6969","uploader":"La10x","categoryP":"audio","categoryS":"other","size":"201904174","seeders":"21","leechers":"11","description":"Howard Stern Show OCT 30 2017 Mon  (04:07:18)\r\n\r\n* Robin Attends A Reveal Party.\r\n* Ronnie&apos;s Birthday Tribute.\r\n* Upcoming Cocktober Event &amp; A Reveal Party Call.\r\n* Howard On TV/Movie Work.\r\n* Goofy Radio Names, &amp; Robin Wants To Sing.\r\n* Cocktober Phony Phone Call To Angry Political Guy.\r\n* TV, Movie Reviews, Sex With Beth, &amp; Fred&apos;s Sexuality.\r\n* Puerto Rico Update &amp; Gun Purchase Recommendation.\r\n* MFB Call, Howard Anti-Semitic Call &amp; Ralph Calls In.\r\n* Baba Booey Bombs.\r\n* Sexual Harassment Allegations &amp; Related Stories.\r\n* Bigfoot Spelling Game, &amp; Another MFB Call.\r\n* A Conversation With Caller Eugene From Kentucky.\r\n* Miss Cocktober Beauty Pageant.\r\n* Miss Cocktober Beauty Pageant Controversey.\r\n* RIP Fats Domino. \r\n* Robin&apos;s News.\r\n\r\n\r\n\r\nWrap Up Show OCT 30 2017 Mon  (32:15)\r\n\r\n* Dr.Drew Sits In.\r\n* Gary&apos;s Throat Clearing.\r\n* Various Ronnie Topics.\r\n* The Miss Cocktober Beauty Pageant.\r\n* Fred&apos;s Do It All Again Comment.\r\n* More Miss Cocktober Beauty Pageant.\r\n* Howard&apos;s Thoughts On Radio Guys Doing TV/Movie Work.\r\n* Sternthology Promo","last_updated":"2017-10-31T12:10:29.374Z","parsed":{"xt":"urn:btih:1df8ad9fefbfdd6ac7ccbf653262179b6d91f851","dn":"Howard Stern Show OCT 30 2017 Mon","tr":["udp://exodus.desync.com:6969","udp://open.demonii.com:1337","udp://tracker.coppersurfer.tk:6969","udp://tracker.leechers-paradise.org:6969","udp://zer0day.ch:1337"],"infoHash":"1df8ad9fefbfdd6ac7ccbf653262179b6d91f851","infoHashBuffer":{"type":"Buffer","data":[29,248,173,159,239,191,221,106,199,204,191,101,50,98,23,155,109,145,248,81]},"name":"Howard Stern Show OCT 30 2017 Mon","announce":["udp://exodus.desync.com:6969","udp://open.demonii.com:1337","udp://tracker.coppersurfer.tk:6969","udp://tracker.leechers-paradise.org:6969","udp://zer0day.ch:1337"],"urlList":[]}}