{"title":"Encyclopedia of Sex And Gender by Fedwa Malti-Douglas","magnet":"magnet:?xt=urn:btih:1ffc9bf362cfe122d2b887b10d490d491d020d00&dn=Encyclopedia+of+Sex+And+Gender+by+Fedwa+Malti-Douglas&tr=udp%3A%2F%2Ftracker.leechers-paradise.org%3A6969&tr=udp%3A%2F%2Fzer0day.ch%3A1337&tr=udp%3A%2F%2Fopen.demonii.com%3A1337&tr=udp%3A%2F%2Ftracker.coppersurfer.tk%3A6969&tr=udp%3A%2F%2Fexodus.desync.com%3A6969","uploader":"spy1984","categoryP":"other","categoryS":"e_books","size":"8131286","seeders":"0","leechers":"0","description":"Encyclopedia of Sex &amp; Gender by Fedwa Malti-Douglas\r\n\r\nEnglish | 405 pages | PDF | 7.75 MB\r\n <a href=\"\nhttp://4kw.in/4059.html\" rel=\"nofollow\" target=\"_NEW\">\nhttp://4kw.in/4059.html</a>\r\n <a href=\"\nhttp://4kw.in/4060.html\" rel=\"nofollow\" target=\"_NEW\">\nhttp://4kw.in/4060.html</a>\r\n <a href=\"\nhttp://4kw.in/4061.html\" rel=\"nofollow\" target=\"_NEW\">\nhttp://4kw.in/4061.html</a>\r\n <a href=\"\nhttp://4kw.in/4062.html\" rel=\"nofollow\" target=\"_NEW\">\nhttp://4kw.in/4062.html</a>","last_updated":"2017-12-30T12:04:11.976Z","parsed":{"xt":"urn:btih:1ffc9bf362cfe122d2b887b10d490d491d020d00","dn":"Encyclopedia of Sex And Gender by Fedwa Malti-Douglas","tr":["udp://exodus.desync.com:6969","udp://open.demonii.com:1337","udp://tracker.coppersurfer.tk:6969","udp://tracker.leechers-paradise.org:6969","udp://zer0day.ch:1337"],"infoHash":"1ffc9bf362cfe122d2b887b10d490d491d020d00","infoHashBuffer":{"type":"Buffer","data":[31,252,155,243,98,207,225,34,210,184,135,177,13,73,13,73,29,2,13,0]},"name":"Encyclopedia of Sex And Gender by Fedwa Malti-Douglas","announce":["udp://exodus.desync.com:6969","udp://open.demonii.com:1337","udp://tracker.coppersurfer.tk:6969","udp://tracker.leechers-paradise.org:6969","udp://zer0day.ch:1337"],"urlList":[]}}