{"title":"The.Fosters.2013.S05E09.WEB.x264-TBS[ettv]","magnet":"magnet:?xt=urn:btih:304ab27e5465d64d4755462b580ad62f3bdfc6f5&dn=The.Fosters.2013.S05E09.WEB.x264-TBS%5Bettv%5D&tr=udp%3A%2F%2Ftracker.leechers-paradise.org%3A6969&tr=udp%3A%2F%2Fzer0day.ch%3A1337&tr=udp%3A%2F%2Fopen.demonii.com%3A1337&tr=udp%3A%2F%2Ftracker.coppersurfer.tk%3A6969&tr=udp%3A%2F%2Fexodus.desync.com%3A6969","uploader":"ettv","categoryP":"video","categoryS":"tv_shows","size":"357279058","seeders":"296","leechers":"97","description":"Et TV Shows\r\n\n\nThe.Fosters.2013.S05E09.WEB.x264-TBS \r\n\n\n[Format]:    Matroska\n[Duration]:    42mn 1s\n[Resolution]:  992 x 558 pixels\n[Display aspect ratio]:    16:9\n[Frame rate mode]:    Variable\n[Original frame rate]:    24.000 fps\n\r\n\n#ettv -&gt; To avoid fakes, ALWAYS check that the torrent was added by ettv\r\n\n\r\n\n\nTo keep us going Support us by donating Bitcoin: 3MDamEmgKepqagtQe9eEdQ3NCrWEWjhoL5\r\n\nScreens...\r <a href=\"\nhttps://extraimage.net/image/TOyx\" rel=\"nofollow\" target=\"_NEW\">\nhttps://extraimage.net/image/TOyx</a>","last_updated":"2017-09-06T12:05:38.917Z","parsed":{"xt":"urn:btih:304ab27e5465d64d4755462b580ad62f3bdfc6f5","dn":"The.Fosters.2013.S05E09.WEB.x264-TBS[ettv]","tr":["udp://exodus.desync.com:6969","udp://open.demonii.com:1337","udp://tracker.coppersurfer.tk:6969","udp://tracker.leechers-paradise.org:6969","udp://zer0day.ch:1337"],"infoHash":"304ab27e5465d64d4755462b580ad62f3bdfc6f5","infoHashBuffer":{"type":"Buffer","data":[48,74,178,126,84,101,214,77,71,85,70,43,88,10,214,47,59,223,198,245]},"name":"The.Fosters.2013.S05E09.WEB.x264-TBS[ettv]","announce":["udp://exodus.desync.com:6969","udp://open.demonii.com:1337","udp://tracker.coppersurfer.tk:6969","udp://tracker.leechers-paradise.org:6969","udp://zer0day.ch:1337"],"urlList":[]}}