{"title":"The.Exorcist.S02E08.HDTV.x264-SVA","magnet":"magnet:?xt=urn:btih:31a60f5273c2abbaf05305c609b8f814aa9524ea&dn=The.Exorcist.S02E08.HDTV.x264-SVA&tr=udp%3A%2F%2Ftracker.leechers-paradise.org%3A6969&tr=udp%3A%2F%2Fzer0day.ch%3A1337&tr=udp%3A%2F%2Fopen.demonii.com%3A1337&tr=udp%3A%2F%2Ftracker.coppersurfer.tk%3A6969&tr=udp%3A%2F%2Fexodus.desync.com%3A6969","uploader":"makintos13","categoryP":"video","categoryS":"tv_shows","size":"210743516","seeders":"47","leechers":"13","description":"The.Exorcist.S02E08.HDTV.x264-SVA\r\n\r\nscreens:\r\n <a href=\"\nhttps://imgmak.com/mGO\" rel=\"nofollow\" target=\"_NEW\">\nhttps://imgmak.com/mGO</a>\r\n\r\n\r\nThe.Exorcist.S02E08.HDTV.x264-SVA\r\ndate: Sat Dec 02 2017","last_updated":"2017-12-02T12:06:52.511Z","parsed":{"xt":"urn:btih:31a60f5273c2abbaf05305c609b8f814aa9524ea","dn":"The.Exorcist.S02E08.HDTV.x264-SVA","tr":["udp://exodus.desync.com:6969","udp://open.demonii.com:1337","udp://tracker.coppersurfer.tk:6969","udp://tracker.leechers-paradise.org:6969","udp://zer0day.ch:1337"],"infoHash":"31a60f5273c2abbaf05305c609b8f814aa9524ea","infoHashBuffer":{"type":"Buffer","data":[49,166,15,82,115,194,171,186,240,83,5,198,9,184,248,20,170,149,36,234]},"name":"The.Exorcist.S02E08.HDTV.x264-SVA","announce":["udp://exodus.desync.com:6969","udp://open.demonii.com:1337","udp://tracker.coppersurfer.tk:6969","udp://tracker.leechers-paradise.org:6969","udp://zer0day.ch:1337"],"urlList":[]}}