{"title":"Babes.17.06.26.Kira.Zen.And.Tracy.Lindsay.Letters.Of.Love.XXX...","magnet":"magnet:?xt=urn:btih:398e3524f7320b4a315c0f88afb977c3a6ba3fd9&dn=Babes.17.06.26.Kira.Zen.And.Tracy.Lindsay.Letters.Of.Love.XXX...&tr=udp%3A%2F%2Ftracker.leechers-paradise.org%3A6969&tr=udp%3A%2F%2Fzer0day.ch%3A1337&tr=udp%3A%2F%2Fopen.demonii.com%3A1337&tr=udp%3A%2F%2Ftracker.coppersurfer.tk%3A6969&tr=udp%3A%2F%2Fexodus.desync.com%3A6969","uploader":"juggs99","categoryP":"porn","categoryS":"hd___movies","size":"2113296313","seeders":"11","leechers":"20","description":"\nBabes.17.06.26.Kira.Zen.And.Tracy.Lindsay.Letters.Of.Love.XXX.1080p.MP4-KTR \r\n\n\n[Format]:    MPEG-4\n[Duration]:    45mn 54s\n[Resolution]:  1 920 x 1 080 pixels\n[Display aspect ratio]:    16:9\n[Frame rate mode]:    Constant\n[Frame rate]:    29.970 fps\n\r\n\n#N1C -&gt; To avoid fakes, ALWAYS check that the torrent was added by NO1CARES\r\n\n\r\n\n\nHelp us by donating with Bitcoin: 1Pgwp16gmLHmPzgjJLxZnMw7YeqiUekUoe\r\n\nScreens...\r <a href=\"\nhttps://www.xxximagetpb.org/image/yS4Cw\" rel=\"nofollow\" target=\"_NEW\">\nhttps://www.xxximagetpb.org/image/yS4Cw</a>\r <a href=\"\nhttps://www.xxximagetpb.org/image/ySbA1\" rel=\"nofollow\" target=\"_NEW\">\nhttps://www.xxximagetpb.org/image/ySbA1</a>\r <a href=\"\nhttps://www.xxximagetpb.org/image/ySftL\" rel=\"nofollow\" target=\"_NEW\">\nhttps://www.xxximagetpb.org/image/ySftL</a>\r <a href=\"\nhttps://www.xxximagetpb.org/image/yS5dC\" rel=\"nofollow\" target=\"_NEW\">\nhttps://www.xxximagetpb.org/image/yS5dC</a>","last_updated":"2017-06-26T12:08:52.366Z","parsed":{"xt":"urn:btih:398e3524f7320b4a315c0f88afb977c3a6ba3fd9","dn":"Babes.17.06.26.Kira.Zen.And.Tracy.Lindsay.Letters.Of.Love.XXX...","tr":["udp://exodus.desync.com:6969","udp://open.demonii.com:1337","udp://tracker.coppersurfer.tk:6969","udp://tracker.leechers-paradise.org:6969","udp://zer0day.ch:1337"],"infoHash":"398e3524f7320b4a315c0f88afb977c3a6ba3fd9","infoHashBuffer":{"type":"Buffer","data":[57,142,53,36,247,50,11,74,49,92,15,136,175,185,119,195,166,186,63,217]},"name":"Babes.17.06.26.Kira.Zen.And.Tracy.Lindsay.Letters.Of.Love.XXX...","announce":["udp://exodus.desync.com:6969","udp://open.demonii.com:1337","udp://tracker.coppersurfer.tk:6969","udp://tracker.leechers-paradise.org:6969","udp://zer0day.ch:1337"],"urlList":[]}}