{"title":"Horny Mature Girlfriend Pose Nice Tits And Pussy","magnet":"magnet:?xt=urn:btih:4679227b0ac8a70e1c512c477719099131277b91&dn=Horny+Mature+Girlfriend+Pose+Nice+Tits+And+Pussy&tr=udp%3A%2F%2Ftracker.leechers-paradise.org%3A6969&tr=udp%3A%2F%2Fzer0day.ch%3A1337&tr=udp%3A%2F%2Fopen.demonii.com%3A1337&tr=udp%3A%2F%2Ftracker.coppersurfer.tk%3A6969&tr=udp%3A%2F%2Fexodus.desync.com%3A6969","uploader":"fstrnu","categoryP":"porn","categoryS":"pictures","size":"298076679","seeders":"0","leechers":"0","description":"Welcome back!!!\r\n\r\nAll amateur sets are original size, always! \r\n\r\nPlease preview 5 random shots from this set on NSFW easy to use preview page:\r\n(right click, open in new tab works great for not losing your place)\r\n                       <a href=\"\nhttp://sampleviews.com/3454\" rel=\"nofollow\" target=\"_NEW\">\nhttp://sampleviews.com/3454</a>\r\n                     <a href=\"\nhttp://torrentpreviews.com/3454\" rel=\"nofollow\" target=\"_NEW\">\nhttp://torrentpreviews.com/3454</a>\r\n                              \r\nClick my name for similar authentic and original amateur files!\r\n\r\n          <a href=\"\nhttps://thepiratebay.org/user/fstrnu/\" rel=\"nofollow\" target=\"_NEW\">\nhttps://thepiratebay.org/user/fstrnu/</a>","last_updated":"2017-08-14T12:00:35.687Z","parsed":{"xt":"urn:btih:4679227b0ac8a70e1c512c477719099131277b91","dn":"Horny Mature Girlfriend Pose Nice Tits And Pussy","tr":["udp://exodus.desync.com:6969","udp://open.demonii.com:1337","udp://tracker.coppersurfer.tk:6969","udp://tracker.leechers-paradise.org:6969","udp://zer0day.ch:1337"],"infoHash":"4679227b0ac8a70e1c512c477719099131277b91","infoHashBuffer":{"type":"Buffer","data":[70,121,34,123,10,200,167,14,28,81,44,71,119,25,9,145,49,39,123,145]},"name":"Horny Mature Girlfriend Pose Nice Tits And Pussy","announce":["udp://exodus.desync.com:6969","udp://open.demonii.com:1337","udp://tracker.coppersurfer.tk:6969","udp://tracker.leechers-paradise.org:6969","udp://zer0day.ch:1337"],"urlList":[]}}