{"title":"Beautiful, very young, big, natural Boobs","magnet":"magnet:?xt=urn:btih:4c31a7fd946d86b8659c2986b41f719910a5b993&dn=Beautiful%2C+very+young%2C+big%2C+natural+Boobs&tr=udp%3A%2F%2Ftracker.leechers-paradise.org%3A6969&tr=udp%3A%2F%2Fzer0day.ch%3A1337&tr=udp%3A%2F%2Fopen.demonii.com%3A1337&tr=udp%3A%2F%2Ftracker.coppersurfer.tk%3A6969&tr=udp%3A%2F%2Fexodus.desync.com%3A6969","uploader":"expressfile","categoryP":"porn","categoryS":"pictures","size":"36523637","seeders":"35","leechers":"10","description":"Beautiful, very young, big, natural Boobs\r\n <a href=\"\nhttp://img.party/img-59bd7938197bc.html\" rel=\"nofollow\" target=\"_NEW\">\nhttp://img.party/img-59bd7938197bc.html</a>\r\n <a href=\"\nhttp://img.party/img-59bd79386495f.html\" rel=\"nofollow\" target=\"_NEW\">\nhttp://img.party/img-59bd79386495f.html</a>\r\n <a href=\"\nhttp://img.party/img-59bd7938bdbfb.html\" rel=\"nofollow\" target=\"_NEW\">\nhttp://img.party/img-59bd7938bdbfb.html</a>\r\n\r\n12.2 Mb - 34 Pictures\r\n\r\nPlease seed and enjoy\r\n\r\nCheck all my torrents\r\n  <a href=\"\nhttp://thepiratebay.se/user/expressfile/\" rel=\"nofollow\" target=\"_NEW\">\nhttp://thepiratebay.se/user/expressfile/</a>","last_updated":"2017-09-17T12:14:58.635Z","parsed":{"xt":"urn:btih:4c31a7fd946d86b8659c2986b41f719910a5b993","dn":"Beautiful, very young, big, natural Boobs","tr":["udp://exodus.desync.com:6969","udp://open.demonii.com:1337","udp://tracker.coppersurfer.tk:6969","udp://tracker.leechers-paradise.org:6969","udp://zer0day.ch:1337"],"infoHash":"4c31a7fd946d86b8659c2986b41f719910a5b993","infoHashBuffer":{"type":"Buffer","data":[76,49,167,253,148,109,134,184,101,156,41,134,180,31,113,153,16,165,185,147]},"name":"Beautiful, very young, big, natural Boobs","announce":["udp://exodus.desync.com:6969","udp://open.demonii.com:1337","udp://tracker.coppersurfer.tk:6969","udp://tracker.leechers-paradise.org:6969","udp://zer0day.ch:1337"],"urlList":[]}}