{"title":"Pantyhosed4U.17.07.12.Ashleigh.Mckenzie.Pantyhosed.Housewife.Bi","magnet":"magnet:?xt=urn:btih:4f0051d641510e058ca95a80146eceea5ea8dc71&dn=Pantyhosed4U.17.07.12.Ashleigh.Mckenzie.Pantyhosed.Housewife.Bi&tr=udp%3A%2F%2Ftracker.leechers-paradise.org%3A6969&tr=udp%3A%2F%2Fzer0day.ch%3A1337&tr=udp%3A%2F%2Fopen.demonii.com%3A1337&tr=udp%3A%2F%2Ftracker.coppersurfer.tk%3A6969&tr=udp%3A%2F%2Fexodus.desync.com%3A6969","uploader":"WankPorn","categoryP":"porn","categoryS":"hd___movies","size":"1194099615","seeders":"0","leechers":"0","description":"Pantyhosed4U.17.07.12.Ashleigh.Mckenzie.Pantyhosed.Housewife.Bitch.XXX.1080p.MP4-KTR\n\n\n{Duration} : 16 min 9 s\n{Format} : MPEG-4\n{Resolution} : 1920 x 1080 pixels\n{Aspect Ratio} : 16:9\n{Frame Rate} : 25.000 fps\n\n\nThumbnails : -\n <a href=\"\nhttps://hot.sizzlingclicks.com/image/ryLL\" rel=\"nofollow\" target=\"_NEW\">\nhttps://hot.sizzlingclicks.com/image/ryLL</a> <a href=\"\nhttps://hot.sizzlingclicks.com/image/rzZ7\" rel=\"nofollow\" target=\"_NEW\">\nhttps://hot.sizzlingclicks.com/image/rzZ7</a> <a href=\"\nhttps://hot.sizzlingclicks.com/image/rGPV\" rel=\"nofollow\" target=\"_NEW\">\nhttps://hot.sizzlingclicks.com/image/rGPV</a> <a href=\"\nhttps://hot.sizzlingclicks.com/image/rg3E\" rel=\"nofollow\" target=\"_NEW\">\nhttps://hot.sizzlingclicks.com/image/rg3E</a>","last_updated":"2017-07-12T12:05:02.088Z","parsed":{"xt":"urn:btih:4f0051d641510e058ca95a80146eceea5ea8dc71","dn":"Pantyhosed4U.17.07.12.Ashleigh.Mckenzie.Pantyhosed.Housewife.Bi","tr":["udp://exodus.desync.com:6969","udp://open.demonii.com:1337","udp://tracker.coppersurfer.tk:6969","udp://tracker.leechers-paradise.org:6969","udp://zer0day.ch:1337"],"infoHash":"4f0051d641510e058ca95a80146eceea5ea8dc71","infoHashBuffer":{"type":"Buffer","data":[79,0,81,214,65,81,14,5,140,169,90,128,20,110,206,234,94,168,220,113]},"name":"Pantyhosed4U.17.07.12.Ashleigh.Mckenzie.Pantyhosed.Housewife.Bi","announce":["udp://exodus.desync.com:6969","udp://open.demonii.com:1337","udp://tracker.coppersurfer.tk:6969","udp://tracker.leechers-paradise.org:6969","udp://zer0day.ch:1337"],"urlList":[]}}