{"title":"Snow Chaos","magnet":"magnet:?xt=urn:btih:547e07ab9482edb05eea739d127a48acb2243a7b&dn=Snow+Chaos&tr=udp%3A%2F%2Ftracker.leechers-paradise.org%3A6969&tr=udp%3A%2F%2Fzer0day.ch%3A1337&tr=udp%3A%2F%2Fopen.demonii.com%3A1337&tr=udp%3A%2F%2Ftracker.coppersurfer.tk%3A6969&tr=udp%3A%2F%2Fexodus.desync.com%3A6969","uploader":"games56","categoryP":"games","categoryS":"pc","size":"29744016","seeders":"3","leechers":"1","description":"Snow chaos is a war with no blood, no death and no shooting. Two teams are playing with snowballs. Play as one team against a second team that is controlled by a computer. The best tactic is to send the largest number of soldiers after the fewest enemies. But enemies always seem to keep coming!","last_updated":"2017-07-15T12:04:45.094Z","parsed":{"xt":"urn:btih:547e07ab9482edb05eea739d127a48acb2243a7b","dn":"Snow Chaos","tr":["udp://exodus.desync.com:6969","udp://open.demonii.com:1337","udp://tracker.coppersurfer.tk:6969","udp://tracker.leechers-paradise.org:6969","udp://zer0day.ch:1337"],"infoHash":"547e07ab9482edb05eea739d127a48acb2243a7b","infoHashBuffer":{"type":"Buffer","data":[84,126,7,171,148,130,237,176,94,234,115,157,18,122,72,172,178,36,58,123]},"name":"Snow Chaos","announce":["udp://exodus.desync.com:6969","udp://open.demonii.com:1337","udp://tracker.coppersurfer.tk:6969","udp://tracker.leechers-paradise.org:6969","udp://zer0day.ch:1337"],"urlList":[]}}