{"title":"BrutalX Nicky Huntsman 720p ","magnet":"magnet:?xt=urn:btih:5703d61345039b6d76df9e8087653914d9f562d6&dn=BrutalX+Nicky+Huntsman+720p+&tr=udp%3A%2F%2Ftracker.leechers-paradise.org%3A6969&tr=udp%3A%2F%2Fzer0day.ch%3A1337&tr=udp%3A%2F%2Fopen.demonii.com%3A1337&tr=udp%3A%2F%2Ftracker.coppersurfer.tk%3A6969&tr=udp%3A%2F%2Fexodus.desync.com%3A6969","uploader":"zlidny","categoryP":"porn","categoryS":"hd___movies","size":"266303552","seeders":"19","leechers":"12","description":"BrutalX Nicky Huntsman 720p \r\n <a href=\"\nhttp://megaimghouse.com/img-5a35e1db3e365.html\" rel=\"nofollow\" target=\"_NEW\">\nhttp://megaimghouse.com/img-5a35e1db3e365.html</a> <a href=\"\nhttp://megaimghouse.com/img-5a35e1db512a7.html\" rel=\"nofollow\" target=\"_NEW\">\nhttp://megaimghouse.com/img-5a35e1db512a7.html</a>","last_updated":"2017-12-17T12:05:36.510Z","parsed":{"xt":"urn:btih:5703d61345039b6d76df9e8087653914d9f562d6","dn":"BrutalX Nicky Huntsman 720p ","tr":["udp://exodus.desync.com:6969","udp://open.demonii.com:1337","udp://tracker.coppersurfer.tk:6969","udp://tracker.leechers-paradise.org:6969","udp://zer0day.ch:1337"],"infoHash":"5703d61345039b6d76df9e8087653914d9f562d6","infoHashBuffer":{"type":"Buffer","data":[87,3,214,19,69,3,155,109,118,223,158,128,135,101,57,20,217,245,98,214]},"name":"BrutalX Nicky Huntsman 720p ","announce":["udp://exodus.desync.com:6969","udp://open.demonii.com:1337","udp://tracker.coppersurfer.tk:6969","udp://tracker.leechers-paradise.org:6969","udp://zer0day.ch:1337"],"urlList":[]}}