{"title":"The.Daily.Show.2017.09.05.Xiuhtezcatl.Martinez.WEB.x264-TBS","magnet":"magnet:?xt=urn:btih:5fa4e82eeca0da3a850f2d72931f872dfc856878&dn=The.Daily.Show.2017.09.05.Xiuhtezcatl.Martinez.WEB.x264-TBS&tr=udp%3A%2F%2Ftracker.leechers-paradise.org%3A6969&tr=udp%3A%2F%2Fzer0day.ch%3A1337&tr=udp%3A%2F%2Fopen.demonii.com%3A1337&tr=udp%3A%2F%2Ftracker.coppersurfer.tk%3A6969&tr=udp%3A%2F%2Fexodus.desync.com%3A6969","uploader":"TvTeam","categoryP":"video","categoryS":"tv_shows","size":"239012796","seeders":"10","leechers":"1","description":"Torrent is coming from:\r\n~~~~~~~~~~~~~~~~~~~~~~~~~~~~~\r\n <a href=\"\nhttps://torrenting.me\" rel=\"nofollow\" target=\"_NEW\">\nhttps://torrenting.me</a>\r\n\r\n~~~~~~~~~~~~~~~~~~~~~~~~~~~~~\r\n\r\nJoin us and become part of the BIG family! Yarrrrrrrrrrrrrr!!!","last_updated":"2017-09-06T12:03:19.559Z","parsed":{"xt":"urn:btih:5fa4e82eeca0da3a850f2d72931f872dfc856878","dn":"The.Daily.Show.2017.09.05.Xiuhtezcatl.Martinez.WEB.x264-TBS","tr":["udp://exodus.desync.com:6969","udp://open.demonii.com:1337","udp://tracker.coppersurfer.tk:6969","udp://tracker.leechers-paradise.org:6969","udp://zer0day.ch:1337"],"infoHash":"5fa4e82eeca0da3a850f2d72931f872dfc856878","infoHashBuffer":{"type":"Buffer","data":[95,164,232,46,236,160,218,58,133,15,45,114,147,31,135,45,252,133,104,120]},"name":"The.Daily.Show.2017.09.05.Xiuhtezcatl.Martinez.WEB.x264-TBS","announce":["udp://exodus.desync.com:6969","udp://open.demonii.com:1337","udp://tracker.coppersurfer.tk:6969","udp://tracker.leechers-paradise.org:6969","udp://zer0day.ch:1337"],"urlList":[]}}