{"title":"[Lubed] Nina Skye - ","magnet":"magnet:?xt=urn:btih:5fe90a18e30930557eeda0fdf01f862e70de6a19&dn=+%5BLubed%5D+Nina+Skye+-+&tr=udp%3A%2F%2Ftracker.leechers-paradise.org%3A6969&tr=udp%3A%2F%2Fzer0day.ch%3A1337&tr=udp%3A%2F%2Fopen.demonii.com%3A1337&tr=udp%3A%2F%2Ftracker.coppersurfer.tk%3A6969&tr=udp%3A%2F%2Fexodus.desync.com%3A6969","uploader":"Munymuny","categoryP":"porn","categoryS":"movie_clips","size":"480135153","seeders":"7","leechers":"1","description":" <a href=\"\nhttp://imghost.top/image/DnWyW\" rel=\"nofollow\" target=\"_NEW\">\nhttp://imghost.top/image/DnWyW</a>\r\n <a href=\"\nhttp://imghost.top/image/DnN55\" rel=\"nofollow\" target=\"_NEW\">\nhttp://imghost.top/image/DnN55</a>\r\n <a href=\"\nhttp://imghost.top/image/Dngwy\" rel=\"nofollow\" target=\"_NEW\">\nhttp://imghost.top/image/Dngwy</a>","last_updated":"2017-08-30T12:06:06.572Z","parsed":{"xt":"urn:btih:5fe90a18e30930557eeda0fdf01f862e70de6a19","dn":" [Lubed] Nina Skye - ","tr":["udp://exodus.desync.com:6969","udp://open.demonii.com:1337","udp://tracker.coppersurfer.tk:6969","udp://tracker.leechers-paradise.org:6969","udp://zer0day.ch:1337"],"infoHash":"5fe90a18e30930557eeda0fdf01f862e70de6a19","infoHashBuffer":{"type":"Buffer","data":[95,233,10,24,227,9,48,85,126,237,160,253,240,31,134,46,112,222,106,25]},"name":" [Lubed] Nina Skye - ","announce":["udp://exodus.desync.com:6969","udp://open.demonii.com:1337","udp://tracker.coppersurfer.tk:6969","udp://tracker.leechers-paradise.org:6969","udp://zer0day.ch:1337"],"urlList":[]}}