{"title":"The Witcher 2 - Assassins of Kings Enhanced Edition v3.4.4.1-GOG","magnet":"magnet:?xt=urn:btih:61b60a3b8d25e347d8dabb9986e579dad335274a&dn=The+Witcher+2+-+Assassins+of+Kings+Enhanced+Edition+v3.4.4.1-GOG&tr=udp%3A%2F%2Ftracker.leechers-paradise.org%3A6969&tr=udp%3A%2F%2Fzer0day.ch%3A1337&tr=udp%3A%2F%2Fopen.demonii.com%3A1337&tr=udp%3A%2F%2Ftracker.coppersurfer.tk%3A6969&tr=udp%3A%2F%2Fexodus.desync.com%3A6969","uploader":"Mr.Masami","categoryP":"games","categoryS":"pc","size":"11150819328","seeders":"28","leechers":"14","description":"Title: The Witcher 2 - Assassins of Kings Enhanced Edition\nGenre: Sexual Content, Nudity, Violent, Gore, Action, Adventure\nDeveloper: CD Projekt RED\nPublisher: Bandai Namco Entertainment \nRelease Date: 17 May, 2011\n\nRePack Info:\n\nStrong compression using precomp, srep and arc.\nDecompression should take ~20min on a decent machine.\n\nInstallation:\n\n1. Mount the .ISO image using daemon tools or unpack it using winrar.\n2. Install the game like every other.\n3. Enjoy &amp; Seed ;)","last_updated":"2018-01-08T12:07:24.652Z","parsed":{"xt":"urn:btih:61b60a3b8d25e347d8dabb9986e579dad335274a","dn":"The Witcher 2 - Assassins of Kings Enhanced Edition v3.4.4.1-GOG","tr":["udp://exodus.desync.com:6969","udp://open.demonii.com:1337","udp://tracker.coppersurfer.tk:6969","udp://tracker.leechers-paradise.org:6969","udp://zer0day.ch:1337"],"infoHash":"61b60a3b8d25e347d8dabb9986e579dad335274a","infoHashBuffer":{"type":"Buffer","data":[97,182,10,59,141,37,227,71,216,218,187,153,134,229,121,218,211,53,39,74]},"name":"The Witcher 2 - Assassins of Kings Enhanced Edition v3.4.4.1-GOG","announce":["udp://exodus.desync.com:6969","udp://open.demonii.com:1337","udp://tracker.coppersurfer.tk:6969","udp://tracker.leechers-paradise.org:6969","udp://zer0day.ch:1337"],"urlList":[]}}