{"title":"Manuels Maximum Penetration 4/4 maximum penetration Manuel (Manu","magnet":"magnet:?xt=urn:btih:65d867383893a6e91891d8136af1602236c51b18&dn=Manuels+Maximum+Penetration+4%2F4+maximum+penetration+Manuel+%28Manu&tr=udp%3A%2F%2Ftracker.leechers-paradise.org%3A6969&tr=udp%3A%2F%2Fzer0day.ch%3A1337&tr=udp%3A%2F%2Fopen.demonii.com%3A1337&tr=udp%3A%2F%2Ftracker.coppersurfer.tk%3A6969&tr=udp%3A%2F%2Fexodus.desync.com%3A6969","uploader":"NewPornUp","categoryP":"porn","categoryS":"movies","size":"1781743908","seeders":"0","leechers":"0","description":"Manuels Maximum Penetration 4/4 maximum penetration Manuel (Manuel Ferrara, Jules Jordan Video) [2017, DVDRip]\r\n\r\nScreenshots :\r\n <a href=\"\nhttp://newpornup.com/img-595b75d60e236.html\" rel=\"nofollow\" target=\"_NEW\">\nhttp://newpornup.com/img-595b75d60e236.html</a>\r\n <a href=\"\nhttp://newpornup.com/img-595b75d62859a.html\" rel=\"nofollow\" target=\"_NEW\">\nhttp://newpornup.com/img-595b75d62859a.html</a>","last_updated":"2017-07-04T12:00:27.915Z","parsed":{"xt":"urn:btih:65d867383893a6e91891d8136af1602236c51b18","dn":"Manuels Maximum Penetration 4/4 maximum penetration Manuel (Manu","tr":["udp://exodus.desync.com:6969","udp://open.demonii.com:1337","udp://tracker.coppersurfer.tk:6969","udp://tracker.leechers-paradise.org:6969","udp://zer0day.ch:1337"],"infoHash":"65d867383893a6e91891d8136af1602236c51b18","infoHashBuffer":{"type":"Buffer","data":[101,216,103,56,56,147,166,233,24,145,216,19,106,241,96,34,54,197,27,24]},"name":"Manuels Maximum Penetration 4/4 maximum penetration Manuel (Manu","announce":["udp://exodus.desync.com:6969","udp://open.demonii.com:1337","udp://tracker.coppersurfer.tk:6969","udp://tracker.leechers-paradise.org:6969","udp://zer0day.ch:1337"],"urlList":[]}}