{"title":"Flatliners (2017) 1080p BRRip 6CH 2GB","magnet":"magnet:?xt=urn:btih:6c0872df08daa5e0e404489456b8f69cb9737177&dn=Flatliners+%282017%29+1080p+BRRip+6CH+2GB&tr=udp%3A%2F%2Ftracker.leechers-paradise.org%3A6969&tr=udp%3A%2F%2Fzer0day.ch%3A1337&tr=udp%3A%2F%2Fopen.demonii.com%3A1337&tr=udp%3A%2F%2Ftracker.coppersurfer.tk%3A6969&tr=udp%3A%2F%2Fexodus.desync.com%3A6969","uploader":"makintos13","categoryP":"video","categoryS":"hd___movies","size":"2216834347","seeders":"2","leechers":"28","description":"Flatliners (2017) 1080p BRRip 6CH 2GB\r\n\r\nscreens:\r\n\r\n <a href=\"\nhttps://imgmak.com/mAZ\" rel=\"nofollow\" target=\"_NEW\">\nhttps://imgmak.com/mAZ</a>\r\n  <a href=\"\nhttps://imgmak.com/mAc\" rel=\"nofollow\" target=\"_NEW\">\nhttps://imgmak.com/mAc</a>\r\n  <a href=\"\nhttps://imgmak.com/mAn\" rel=\"nofollow\" target=\"_NEW\">\nhttps://imgmak.com/mAn</a>\r\n\r\nMovie Title: Flatliners (2017)\r\nDirector: Niels Arden Oplev\r\nStars: Ellen Page, Diego Luna, Nina Dobrev\r\nRelease Date: 29 September 2017 (UK)\r\nGenres: Drama, Horror, Sci-Fi \r\nFormat: MatRoska (Mkv)\r\nFile Size: 2GB\r\nResolution: 1920x800\r\nRuntime: 01:49:46\r\nLanguage: English\r\nSubtitles: English [Softcoded] - Muxed\r\n\r\nSource: 1080p.BluRay.x264-GECKOS","last_updated":"2017-12-12T12:00:42.223Z","parsed":{"xt":"urn:btih:6c0872df08daa5e0e404489456b8f69cb9737177","dn":"Flatliners (2017) 1080p BRRip 6CH 2GB","tr":["udp://exodus.desync.com:6969","udp://open.demonii.com:1337","udp://tracker.coppersurfer.tk:6969","udp://tracker.leechers-paradise.org:6969","udp://zer0day.ch:1337"],"infoHash":"6c0872df08daa5e0e404489456b8f69cb9737177","infoHashBuffer":{"type":"Buffer","data":[108,8,114,223,8,218,165,224,228,4,72,148,86,184,246,156,185,115,113,119]},"name":"Flatliners (2017) 1080p BRRip 6CH 2GB","announce":["udp://exodus.desync.com:6969","udp://open.demonii.com:1337","udp://tracker.coppersurfer.tk:6969","udp://tracker.leechers-paradise.org:6969","udp://zer0day.ch:1337"],"urlList":[]}}