{"title":"NHDTA-998 or squeezed press! 2 was a mad Pies and neat and clean","magnet":"magnet:?xt=urn:btih:746dc213dd6b4734440fe808f6edb64165fba216&dn=NHDTA-998+or+squeezed+press%21+2+was+a+mad+Pies+and+neat+and+clean&tr=udp%3A%2F%2Ftracker.leechers-paradise.org%3A6969&tr=udp%3A%2F%2Fzer0day.ch%3A1337&tr=udp%3A%2F%2Fopen.demonii.com%3A1337&tr=udp%3A%2F%2Ftracker.coppersurfer.tk%3A6969&tr=udp%3A%2F%2Fexodus.desync.com%3A6969","uploader":"NewPornUp","categoryP":"porn","categoryS":"hd___movies","size":"5292555485","seeders":"43","leechers":"129","description":"NHDTA-998 or squeezed press! 2 was a mad Pies and neat and clean face If you committed the next Big sister\r\n\r\nScreenshots :\r\n <a href=\"\nhttp://newpornup.com/img-594cce0560817.html\" rel=\"nofollow\" target=\"_NEW\">\nhttp://newpornup.com/img-594cce0560817.html</a>\r\n <a href=\"\nhttp://newpornup.com/img-594cce0564bf7.html\" rel=\"nofollow\" target=\"_NEW\">\nhttp://newpornup.com/img-594cce0564bf7.html</a>","last_updated":"2017-06-23T12:02:34.547Z","parsed":{"xt":"urn:btih:746dc213dd6b4734440fe808f6edb64165fba216","dn":"NHDTA-998 or squeezed press! 2 was a mad Pies and neat and clean","tr":["udp://exodus.desync.com:6969","udp://open.demonii.com:1337","udp://tracker.coppersurfer.tk:6969","udp://tracker.leechers-paradise.org:6969","udp://zer0day.ch:1337"],"infoHash":"746dc213dd6b4734440fe808f6edb64165fba216","infoHashBuffer":{"type":"Buffer","data":[116,109,194,19,221,107,71,52,68,15,232,8,246,237,182,65,101,251,162,22]},"name":"NHDTA-998 or squeezed press! 2 was a mad Pies and neat and clean","announce":["udp://exodus.desync.com:6969","udp://open.demonii.com:1337","udp://tracker.coppersurfer.tk:6969","udp://tracker.leechers-paradise.org:6969","udp://zer0day.ch:1337"],"urlList":[]}}