{"title":"Malwarebytes Anti-Exploit for Business 1.09.2.1261 + Serials","magnet":"magnet:?xt=urn:btih:79128b4ffd52c0145ff2482c623d95bf1f1865f4&dn=Malwarebytes+Anti-Exploit+for+Business+1.09.2.1261+%2B+Serials&tr=udp%3A%2F%2Ftracker.leechers-paradise.org%3A6969&tr=udp%3A%2F%2Fzer0day.ch%3A1337&tr=udp%3A%2F%2Fopen.demonii.com%3A1337&tr=udp%3A%2F%2Ftracker.coppersurfer.tk%3A6969&tr=udp%3A%2F%2Fexodus.desync.com%3A6969","uploader":"lucuos","categoryP":"applications","categoryS":"windows","size":"24875679","seeders":"5776","leechers":"649","description":"\r\n\r\n\r\n\r\n1) Unpack and install\r\n2) Use the key generator to generate a valid serial\r\n3) Enjoy this release!\r\n\r\nDon&apos;t Forget to buy the program","last_updated":"2017-07-26T12:01:35.804Z","parsed":{"xt":"urn:btih:79128b4ffd52c0145ff2482c623d95bf1f1865f4","dn":"Malwarebytes Anti-Exploit for Business 1.09.2.1261   Serials","tr":["udp://exodus.desync.com:6969","udp://open.demonii.com:1337","udp://tracker.coppersurfer.tk:6969","udp://tracker.leechers-paradise.org:6969","udp://zer0day.ch:1337"],"infoHash":"79128b4ffd52c0145ff2482c623d95bf1f1865f4","infoHashBuffer":{"type":"Buffer","data":[121,18,139,79,253,82,192,20,95,242,72,44,98,61,149,191,31,24,101,244]},"name":"Malwarebytes Anti-Exploit for Business 1.09.2.1261   Serials","announce":["udp://exodus.desync.com:6969","udp://open.demonii.com:1337","udp://tracker.coppersurfer.tk:6969","udp://tracker.leechers-paradise.org:6969","udp://zer0day.ch:1337"],"urlList":[]}}