{"title":"Ashanti Big Booty Dutch Ebony Teen","magnet":"magnet:?xt=urn:btih:81f53adb3a6b09605d0bd25e2cdb1a3aebc22aa4&dn=Ashanti+Big+Booty+Dutch+Ebony+Teen&tr=udp%3A%2F%2Ftracker.leechers-paradise.org%3A6969&tr=udp%3A%2F%2Fzer0day.ch%3A1337&tr=udp%3A%2F%2Fopen.demonii.com%3A1337&tr=udp%3A%2F%2Ftracker.coppersurfer.tk%3A6969&tr=udp%3A%2F%2Fexodus.desync.com%3A6969","uploader":"ompeom","categoryP":"porn","categoryS":"movie_clips","size":"105306522","seeders":"15","leechers":"5","description":"Description\r\n\r\nFile Name -  Ashanti Big Booty Dutch Ebony Teen\r\nResolution -  640*360\r\nSize -        99.4 MB\r\nRuntime -     31 Min 48 Sec\r\nFile Formet - MP4,Best Player To Play ( VLC )\r\n\r\nSample Images\r\n\r\n <a href=\"\nhttp://socialporn.online/2017/06/11/2838/\" rel=\"nofollow\" target=\"_NEW\">\nhttp://socialporn.online/2017/06/11/2838/</a> <a href=\"\nhttp://socialporn.online/2017/06/11/2839/\" rel=\"nofollow\" target=\"_NEW\">\nhttp://socialporn.online/2017/06/11/2839/</a>","last_updated":"2017-06-11T12:05:29.902Z","parsed":{"xt":"urn:btih:81f53adb3a6b09605d0bd25e2cdb1a3aebc22aa4","dn":"Ashanti Big Booty Dutch Ebony Teen","tr":["udp://exodus.desync.com:6969","udp://open.demonii.com:1337","udp://tracker.coppersurfer.tk:6969","udp://tracker.leechers-paradise.org:6969","udp://zer0day.ch:1337"],"infoHash":"81f53adb3a6b09605d0bd25e2cdb1a3aebc22aa4","infoHashBuffer":{"type":"Buffer","data":[129,245,58,219,58,107,9,96,93,11,210,94,44,219,26,58,235,194,42,164]},"name":"Ashanti Big Booty Dutch Ebony Teen","announce":["udp://exodus.desync.com:6969","udp://open.demonii.com:1337","udp://tracker.coppersurfer.tk:6969","udp://tracker.leechers-paradise.org:6969","udp://zer0day.ch:1337"],"urlList":[]}}