{"title":"[LegalPorno] Belle Claire and Luna Corazon SZ1786 (18.07.2017)","magnet":"magnet:?xt=urn:btih:836e385cd48548d88a67fdee4d78c12bdcbd27e6&dn=%5BLegalPorno%5D+Belle+Claire+and+Luna+Corazon+SZ1786+%2818.07.2017%29&tr=udp%3A%2F%2Ftracker.leechers-paradise.org%3A6969&tr=udp%3A%2F%2Fzer0day.ch%3A1337&tr=udp%3A%2F%2Fopen.demonii.com%3A1337&tr=udp%3A%2F%2Ftracker.coppersurfer.tk%3A6969&tr=udp%3A%2F%2Fexodus.desync.com%3A6969","uploader":"KayWily","categoryP":"porn","categoryS":"movie_clips","size":"1119472141","seeders":"63","leechers":"121","description":"[LegalPorno] Belle Claire &amp; Luna Corazon anal &amp; DP orgy with five guys SZ1786 (18.07.2017)\r\n\r\n <a href=\"\nhttp://porn-harbor.com/image/ucXCt\" rel=\"nofollow\" target=\"_NEW\">\nhttp://porn-harbor.com/image/ucXCt</a>","last_updated":"2017-07-18T12:02:51.978Z","parsed":{"xt":"urn:btih:836e385cd48548d88a67fdee4d78c12bdcbd27e6","dn":"[LegalPorno] Belle Claire and Luna Corazon SZ1786 (18.07.2017)","tr":["udp://exodus.desync.com:6969","udp://open.demonii.com:1337","udp://tracker.coppersurfer.tk:6969","udp://tracker.leechers-paradise.org:6969","udp://zer0day.ch:1337"],"infoHash":"836e385cd48548d88a67fdee4d78c12bdcbd27e6","infoHashBuffer":{"type":"Buffer","data":[131,110,56,92,212,133,72,216,138,103,253,238,77,120,193,43,220,189,39,230]},"name":"[LegalPorno] Belle Claire and Luna Corazon SZ1786 (18.07.2017)","announce":["udp://exodus.desync.com:6969","udp://open.demonii.com:1337","udp://tracker.coppersurfer.tk:6969","udp://tracker.leechers-paradise.org:6969","udp://zer0day.ch:1337"],"urlList":[]}}