{"title":"Billboard Hot Latin Songs Top 40 set2017 [mp3V0]","magnet":"magnet:?xt=urn:btih:8ea1da879e39672ba389aa3609e10398594740f9&dn=Billboard+Hot+Latin+Songs+Top+40+set2017+%5Bmp3V0%5D&tr=udp%3A%2F%2Ftracker.leechers-paradise.org%3A6969&tr=udp%3A%2F%2Fzer0day.ch%3A1337&tr=udp%3A%2F%2Fopen.demonii.com%3A1337&tr=udp%3A%2F%2Ftracker.coppersurfer.tk%3A6969&tr=udp%3A%2F%2Fexodus.desync.com%3A6969","uploader":"KaiserLIMA","categoryP":"audio","categoryS":"other","size":"277557996","seeders":"1","leechers":"0","description":"Format........................ : MPEG Audio Version 1 Layer 3\r\nMode.......................... : Joint stereo\r\nBit rate mode..................: Variable (VBR=0)\r\nBit rate...................... : 250 - 276 Kbps\r\nChannel(s).................... : 2 channels\r\nSampling rate..................: 44.1 KHz\r\n\r\nHF preservation and Psycho-acoustic Process in Adobe Audittion, encoded in ffmpeg and Adobe Media Encoder\r\n\r\n\r\n01 Last Week: 01 Felices Los 4 - Maluma\r\n02 Last Week: 03 Mi Gente - J Balvin &amp; Willy William\r\n03 Last Week: 04 Imitadora - Romeo Santos\r\n04 Last Week: 02 Despacito - Luis Fonsi &amp; Daddy Yankee Featuring Justin Bieber\r\n05 Last Week: 05 Me Enamore - Shakira\r\n06 Last Week: 06 Hey DJ - CNCO &amp; Yandel\r\n07 Last Week: 07 Escapate Conmigo - Wisin Featuring Ozuna\r\n08 Last Week: 09 Que Me Has Hecho - Chayanne Featuring Wisin\r\n09 Last Week: 08 Subeme La Radio - Enrique Iglesias Featuring Descemer Bueno, Zion &amp; Lennox Or Sean Paul\r\n10 Last Week: 10 La Rompe Corazones -  Daddy Yankee X Ozuna\r\n11 Last Week: 13 El Ratico - Juanes Featuring Kali Uchis\r\n12 Last Week: 12 Sigo Extranandote - J Balvin\r\n13 Last Week: 11 El Amante - Nicky Jam\r\n14 Last Week: 15 Bailame - Nacho\r\n15 Last Week: 14 Mi Religion - Yandel\r\n16 Last Week: 16 Si No Vuelves - Gente de Zona\r\n17 Last Week: 20 Si Tu La Ves - Nicky Jam Featuring Wisin\r\n18 Last Week: 17 Ni Tu Ni Yo - Jennifer Lopez Featuring Gente de Zona\r\n19 Last Week: 19 Me Rehuso - Danny Ocean\r\n20 Last Week: 18 Bonita - Jowell &amp; Randy &amp; J. Balvin\r\n21 Last Week: 21 Quedate Conmigo - Chyno Miranda Featuring Wisin y Gente de Zona\r\n22 Last Week: 23 Quiereme - Jacob Forever Featuring Farruko\r\n23 Last Week: 22 Esa Boquita - J Alvarez\r\n24 Last Week: 25 A Ella - Karol G\r\n25 Last Week: 24 Besandote - Piso 21\r\n26 Last Week: 26 Hasta Que Me de La Gana - Victor Manuelle\r\n27 Last Week: 30 Tu Foto - Ozuna\r\n28 Last Week: 38 Dure Dure - Jencarlos + Don Omar\r\n29 Last Week: 28 Te Acuerdas de Mi - Plan B\r\n30 Last Week: 33 Just As I Am - Spiff TV Featuring Prince Royce &amp; Chris Brown\r\n31 Last Week: 31 Ahora Dice - Chris Jeday Presenta J Balvin, Ozuna &amp; Arcangel\r\n32 Last Week: 29 Por Un Beso De Tu Boca - Silvestre Dangond\r\n33 Last Week: 32 Cuando Un Hombre Te Enamora - Gloria Trevi &amp; Alejandra Guzman\r\n34 Last Week: -- Robarte Un Beso - Carlos Vives &amp; Sebastian Yatra\r\n35 Last Week: 35  Azucar Amargo - Pedro Capo\r\n36 Last Week: 36 Loca - Maite Perroni Featuring Cali Dandee\r\n37 Last Week: -- Me Descontrola - Alexis &amp; Fido\r\n38 Last Week: 40  Mayores - Becky G Featuring Bad Bunny\r\n39 Last Week: -- Me Gustas - Kevin Roldan\r\n40 Last Week: 39 Amor - IAmChino Featuring Chacal X Wisin","last_updated":"2017-08-20T12:04:27.841Z","parsed":{"xt":"urn:btih:8ea1da879e39672ba389aa3609e10398594740f9","dn":"Billboard Hot Latin Songs Top 40 set2017 [mp3V0]","tr":["udp://exodus.desync.com:6969","udp://open.demonii.com:1337","udp://tracker.coppersurfer.tk:6969","udp://tracker.leechers-paradise.org:6969","udp://zer0day.ch:1337"],"infoHash":"8ea1da879e39672ba389aa3609e10398594740f9","infoHashBuffer":{"type":"Buffer","data":[142,161,218,135,158,57,103,43,163,137,170,54,9,225,3,152,89,71,64,249]},"name":"Billboard Hot Latin Songs Top 40 set2017 [mp3V0]","announce":["udp://exodus.desync.com:6969","udp://open.demonii.com:1337","udp://tracker.coppersurfer.tk:6969","udp://tracker.leechers-paradise.org:6969","udp://zer0day.ch:1337"],"urlList":[]}}