{"title":"Little Nightmares - Secrets of The Maw Chapter 1 + DLC","magnet":"magnet:?xt=urn:btih:9ce953f418ea0b4e2b0d9ee43522249d7ae908ea&dn=Little+Nightmares+-+Secrets+of+The+Maw+Chapter+1+%2B+DLC&tr=udp%3A%2F%2Ftracker.leechers-paradise.org%3A6969&tr=udp%3A%2F%2Fzer0day.ch%3A1337&tr=udp%3A%2F%2Fopen.demonii.com%3A1337&tr=udp%3A%2F%2Ftracker.coppersurfer.tk%3A6969&tr=udp%3A%2F%2Fexodus.desync.com%3A6969","uploader":"snitschers","categoryP":"games","categoryS":"pc","size":"1998592000","seeders":"0","leechers":"5","description":"Language: English, Russian\r\nRelease date:2017\r\n\r\nSystem Requirements:\r\nOperating system: Windows 7, 8, 10 (64-bit)\r\nProcessor: Intel CPU Core i3\r\nMemory: 4GB\r\nVideo card: Nvidia GTX 460 (DirectX: Version 11)\r\nSound Card: Sound device compatible with DirectX&#xAE; 11\r\nFree space on hard disk: 7.2 GB\r\n\r\nRelease info:\r\nBased on the release of CODEX\r\nDo not cut / Do not recoded\r\nGame version: 1.0\r\nUnlocked DLC:\r\nLittle Nightmares - Scarecrow Sack\r\nLittle Nightmares - Upside-down Teapot\r\nLittle Nightmares - Tengu Mask\r\nLittle Nightmares - DLC Mask\r\nLittle Nightmares - Secrets of The Maw Expansion Pass\r\n&#xBB;Installation time 2 minutes on HDD (depends on the computer)\r\n\r\nFeatures:\r\nStart an ominous adventure - remember your childhood fears in this gloomy bizarre fairy tale with a frightening atmosphere and a lot of unexpected situations.\r\nVisit the Womb - look into the world Sixth, half sleep, half a nightmare, where each step is given as a leap, and every shadow seems impenetrable darkness!\r\nRemember childhood pleasures - wake up a child in yourself, give free rein to the imagination and stay away from dangers. Each room is a cage, each of its inhabitants is a threat, and together it is a problem that you have to solve.\r\n\r\nInstallation:\r\nMount and install\r\nPlay","last_updated":"2017-07-07T12:02:30.352Z","parsed":{"xt":"urn:btih:9ce953f418ea0b4e2b0d9ee43522249d7ae908ea","dn":"Little Nightmares - Secrets of The Maw Chapter 1   DLC","tr":["udp://exodus.desync.com:6969","udp://open.demonii.com:1337","udp://tracker.coppersurfer.tk:6969","udp://tracker.leechers-paradise.org:6969","udp://zer0day.ch:1337"],"infoHash":"9ce953f418ea0b4e2b0d9ee43522249d7ae908ea","infoHashBuffer":{"type":"Buffer","data":[156,233,83,244,24,234,11,78,43,13,158,228,53,34,36,157,122,233,8,234]},"name":"Little Nightmares - Secrets of The Maw Chapter 1   DLC","announce":["udp://exodus.desync.com:6969","udp://open.demonii.com:1337","udp://tracker.coppersurfer.tk:6969","udp://tracker.leechers-paradise.org:6969","udp://zer0day.ch:1337"],"urlList":[]}}