{"title":"\nBlade.Runner.1982.Final.Cu.1080p.BluRay.x264.AAC.5.1-POOP","magnet":"magnet:?xt=urn:btih:ad1cd09bc0d3f0ceb73d1210d1af6e377d6b797a&dn=Blade.Runner.1982.Final.Cu.1080p.BluRay.x264.AAC.5.1-POOP&tr=udp%3A%2F%2Ftracker.leechers-paradise.org%3A6969&tr=udp%3A%2F%2Fzer0day.ch%3A1337&tr=udp%3A%2F%2Fopen.demonii.com%3A1337&tr=udp%3A%2F%2Ftracker.coppersurfer.tk%3A6969&tr=udp%3A%2F%2Fexodus.desync.com%3A6969","uploader":"P_O_O_P","categoryP":"video","categoryS":"hd___movies","size":"2069044614","seeders":"16","leechers":"16","description":" <a href=\"http://www.imdb.com/title/tt0083658/\" rel=\"nofollow\" target=\"_NEW\">http://www.imdb.com/title/tt0083658/</a>","last_updated":"2017-10-01T12:04:52.514Z","parsed":{"xt":"urn:btih:ad1cd09bc0d3f0ceb73d1210d1af6e377d6b797a","dn":"Blade.Runner.1982.Final.Cu.1080p.BluRay.x264.AAC.5.1-POOP","tr":["udp://exodus.desync.com:6969","udp://open.demonii.com:1337","udp://tracker.coppersurfer.tk:6969","udp://tracker.leechers-paradise.org:6969","udp://zer0day.ch:1337"],"infoHash":"ad1cd09bc0d3f0ceb73d1210d1af6e377d6b797a","infoHashBuffer":{"type":"Buffer","data":[173,28,208,155,192,211,240,206,183,61,18,16,209,175,110,55,125,107,121,122]},"name":"Blade.Runner.1982.Final.Cu.1080p.BluRay.x264.AAC.5.1-POOP","announce":["udp://exodus.desync.com:6969","udp://open.demonii.com:1337","udp://tracker.coppersurfer.tk:6969","udp://tracker.leechers-paradise.org:6969","udp://zer0day.ch:1337"],"urlList":[]}}