{"title":"[TsSeduction /Kink] Aubrey Kate & Pierce Paris / ","magnet":"magnet:?xt=urn:btih:ad6bb21fbd30283e68f08e0777eebe05f34cab69&dn=%5BTsSeduction+%2FKink%5D+Aubrey+Kate+%26amp%3B+Pierce+Paris+%2F+&tr=udp%3A%2F%2Ftracker.leechers-paradise.org%3A6969&tr=udp%3A%2F%2Fzer0day.ch%3A1337&tr=udp%3A%2F%2Fopen.demonii.com%3A1337&tr=udp%3A%2F%2Ftracker.coppersurfer.tk%3A6969&tr=udp%3A%2F%2Fexodus.desync.com%3A6969","uploader":"pleki93","categoryP":"porn","categoryS":"movie_clips","size":"452105382","seeders":"0","leechers":"0","description":" <a href=\"http://imghost.top/image/3JKs4\" rel=\"nofollow\" target=\"_NEW\">http://imghost.top/image/3JKs4</a> <a href=\"\nhttp://imghost.top/image/3J76E\" rel=\"nofollow\" target=\"_NEW\">\nhttp://imghost.top/image/3J76E</a>","last_updated":"2017-11-02T12:02:36.064Z","parsed":{"xt":"urn:btih:ad6bb21fbd30283e68f08e0777eebe05f34cab69","dn":"[TsSeduction /Kink] Aubrey Kate &amp; Pierce Paris / ","tr":["udp://exodus.desync.com:6969","udp://open.demonii.com:1337","udp://tracker.coppersurfer.tk:6969","udp://tracker.leechers-paradise.org:6969","udp://zer0day.ch:1337"],"infoHash":"ad6bb21fbd30283e68f08e0777eebe05f34cab69","infoHashBuffer":{"type":"Buffer","data":[173,107,178,31,189,48,40,62,104,240,142,7,119,238,190,5,243,76,171,105]},"name":"[TsSeduction /Kink] Aubrey Kate &amp; Pierce Paris / ","announce":["udp://exodus.desync.com:6969","udp://open.demonii.com:1337","udp://tracker.coppersurfer.tk:6969","udp://tracker.leechers-paradise.org:6969","udp://zer0day.ch:1337"],"urlList":[]}}