{"title":"DPFanatics - Francys Belle (Double Pounding Massage) NEW 01 Dece","magnet":"magnet:?xt=urn:btih:afa55685cf9830d3b4fd6b437f17aeae9c52336a&dn=DPFanatics+-+Francys+Belle+%28Double+Pounding+Massage%29+NEW+01+Dece&tr=udp%3A%2F%2Ftracker.leechers-paradise.org%3A6969&tr=udp%3A%2F%2Fzer0day.ch%3A1337&tr=udp%3A%2F%2Fopen.demonii.com%3A1337&tr=udp%3A%2F%2Ftracker.coppersurfer.tk%3A6969&tr=udp%3A%2F%2Fexodus.desync.com%3A6969","uploader":"xxxlavalxxx","categoryP":"porn","categoryS":"movie_clips","size":"332670384","seeders":"16","leechers":"16","description":"Francys Belle is one hot busty babe. She is coming in today for a deep tissue four hand massage. But she needs something more than that. She wants two rock hard cocks deep inside her simultaneously. She starts by pulling out the massage therapist&apos;s dicks and swallowing them to the back of her throat. Thomas Stone goes on by fucking her sweet pussy while she keeps on sucking John&apos;s shaft. She then gets on top of Thomas to ride his hard shlong and John sticks his dick in her tight bunghole. This is the ultimate pleasure, to have her pink starfish plowed with a second cock in her cooch. She moans in ecstasy as both of her holes are stimulated by firm throbbing knobs. Both guys finish by releasing their loads in Francys&apos;s mouth.\r\nCategories  anal, blowjob, double penetration, threesome, babes, big tits, brunette, cumshot\r\n <a href=\"\nhttp://img.imgdone.com/image/2ajWW\" rel=\"nofollow\" target=\"_NEW\">\nhttp://img.imgdone.com/image/2ajWW</a>\r\n <a href=\"\nhttp://img.imgdone.com/image/2aofH\" rel=\"nofollow\" target=\"_NEW\">\nhttp://img.imgdone.com/image/2aofH</a>","last_updated":"2017-12-01T12:07:25.743Z","parsed":{"xt":"urn:btih:afa55685cf9830d3b4fd6b437f17aeae9c52336a","dn":"DPFanatics - Francys Belle (Double Pounding Massage) NEW 01 Dece","tr":["udp://exodus.desync.com:6969","udp://open.demonii.com:1337","udp://tracker.coppersurfer.tk:6969","udp://tracker.leechers-paradise.org:6969","udp://zer0day.ch:1337"],"infoHash":"afa55685cf9830d3b4fd6b437f17aeae9c52336a","infoHashBuffer":{"type":"Buffer","data":[175,165,86,133,207,152,48,211,180,253,107,67,127,23,174,174,156,82,51,106]},"name":"DPFanatics - Francys Belle (Double Pounding Massage) NEW 01 Dece","announce":["udp://exodus.desync.com:6969","udp://open.demonii.com:1337","udp://tracker.coppersurfer.tk:6969","udp://tracker.leechers-paradise.org:6969","udp://zer0day.ch:1337"],"urlList":[]}}