{"title":"[Bang! Casting / Bang! Originals] Rachel James ","magnet":"magnet:?xt=urn:btih:b4a84cd4d53e248d964ed4b4cbd86259eae90fa0&dn=%5BBang%21+Casting+%2F+Bang%21+Originals%5D+Rachel+James+&tr=udp%3A%2F%2Ftracker.leechers-paradise.org%3A6969&tr=udp%3A%2F%2Fzer0day.ch%3A1337&tr=udp%3A%2F%2Fopen.demonii.com%3A1337&tr=udp%3A%2F%2Ftracker.coppersurfer.tk%3A6969&tr=udp%3A%2F%2Fexodus.desync.com%3A6969","uploader":"ritabut","categoryP":"porn","categoryS":"movie_clips","size":"1107730350","seeders":"6","leechers":"4","description":" <a href=\"\nhttp://picshits.com/img-59b633995ec85.html\" rel=\"nofollow\" target=\"_NEW\">\nhttp://picshits.com/img-59b633995ec85.html</a> <a href=\"\nhttp://picshits.com/img-59b63399629d7.html\" rel=\"nofollow\" target=\"_NEW\">\nhttp://picshits.com/img-59b63399629d7.html</a>","last_updated":"2017-09-11T12:03:34.982Z","parsed":{"xt":"urn:btih:b4a84cd4d53e248d964ed4b4cbd86259eae90fa0","dn":"[Bang! Casting / Bang! Originals] Rachel James ","tr":["udp://exodus.desync.com:6969","udp://open.demonii.com:1337","udp://tracker.coppersurfer.tk:6969","udp://tracker.leechers-paradise.org:6969","udp://zer0day.ch:1337"],"infoHash":"b4a84cd4d53e248d964ed4b4cbd86259eae90fa0","infoHashBuffer":{"type":"Buffer","data":[180,168,76,212,213,62,36,141,150,78,212,180,203,216,98,89,234,233,15,160]},"name":"[Bang! Casting / Bang! Originals] Rachel James ","announce":["udp://exodus.desync.com:6969","udp://open.demonii.com:1337","udp://tracker.coppersurfer.tk:6969","udp://tracker.leechers-paradise.org:6969","udp://zer0day.ch:1337"],"urlList":[]}}