{"title":"SlySoft AnyDVD HD v7.6.9.2 FINAL + Key","magnet":"magnet:?xt=urn:btih:b963d46a19a1ee52fe94f3abc688635dbce107db&dn=SlySoft+AnyDVD+HD+v7.6.9.2+FINAL+%2B+Key&tr=udp%3A%2F%2Ftracker.leechers-paradise.org%3A6969&tr=udp%3A%2F%2Fzer0day.ch%3A1337&tr=udp%3A%2F%2Fopen.demonii.com%3A1337&tr=udp%3A%2F%2Ftracker.coppersurfer.tk%3A6969&tr=udp%3A%2F%2Fexodus.desync.com%3A6969","uploader":"bborah","categoryP":"software","categoryS":"windows","size":"4035220","seeders":"5273","leechers":"553","description":"\r\n\r\n\r\n\r\n1) Unpack and install\r\n2) Use the key generator to generate a valid serial\r\n3) Enjoy this release!\r\n\r\nDon&apos;t Forget to buy the program","last_updated":"2017-08-03T12:01:27.496Z","parsed":{"xt":"urn:btih:b963d46a19a1ee52fe94f3abc688635dbce107db","dn":"SlySoft AnyDVD HD v7.6.9.2 FINAL   Key","tr":["udp://exodus.desync.com:6969","udp://open.demonii.com:1337","udp://tracker.coppersurfer.tk:6969","udp://tracker.leechers-paradise.org:6969","udp://zer0day.ch:1337"],"infoHash":"b963d46a19a1ee52fe94f3abc688635dbce107db","infoHashBuffer":{"type":"Buffer","data":[185,99,212,106,25,161,238,82,254,148,243,171,198,136,99,93,188,225,7,219]},"name":"SlySoft AnyDVD HD v7.6.9.2 FINAL   Key","announce":["udp://exodus.desync.com:6969","udp://open.demonii.com:1337","udp://tracker.coppersurfer.tk:6969","udp://tracker.leechers-paradise.org:6969","udp://zer0day.ch:1337"],"urlList":[]}}