{"title":"WildOnCam 17 08 02 Marica Hase And Natasha Starr XXX 480p MP4-T","magnet":"magnet:?xt=urn:btih:b9db10be5bab1226fbe708b8989706ea0836e786&dn=WildOnCam+17+08+02+Marica+Hase+And+Natasha+Starr+XXX+480p+MP4-T&tr=udp%3A%2F%2Ftracker.leechers-paradise.org%3A6969&tr=udp%3A%2F%2Fzer0day.ch%3A1337&tr=udp%3A%2F%2Fopen.demonii.com%3A1337&tr=udp%3A%2F%2Ftracker.coppersurfer.tk%3A6969&tr=udp%3A%2F%2Fexodus.desync.com%3A6969","uploader":"XXX_TK","categoryP":"porn","categoryS":"movie_clips","size":"523616897","seeders":"0","leechers":"0","description":"WildOnCam 17 08 02 Marica Hase And Natasha Starr XXX 480p MP4-TK\n\nScreenshots:\n <a href=\"\nhttp://imagerar.com/img-5981b6c4f0587.html\" rel=\"nofollow\" target=\"_NEW\">\nhttp://imagerar.com/img-5981b6c4f0587.html</a>\n <a href=\"\nhttp://imagerar.com/img-5981b6c4ee3eb.html\" rel=\"nofollow\" target=\"_NEW\">\nhttp://imagerar.com/img-5981b6c4ee3eb.html</a>\n <a href=\"\nhttp://imagerar.com/img-5981b6c4ec295.html\" rel=\"nofollow\" target=\"_NEW\">\nhttp://imagerar.com/img-5981b6c4ec295.html</a>\n <a href=\"\nhttp://imagerar.com/img-5981b6c43762f.html\" rel=\"nofollow\" target=\"_NEW\">\nhttp://imagerar.com/img-5981b6c43762f.html</a>\n\n\nFile Size : 499 MiB\nDuration : 1h 0mn\nVideo : h264, yuv420p, 854x480p, 1024 Kbps\nAudio : aac , 2 ch, stereo , 128 Kbps","last_updated":"2017-08-02T12:00:29.996Z","parsed":{"xt":"urn:btih:b9db10be5bab1226fbe708b8989706ea0836e786","dn":"WildOnCam 17 08 02 Marica Hase And Natasha Starr XXX 480p MP4-T","tr":["udp://exodus.desync.com:6969","udp://open.demonii.com:1337","udp://tracker.coppersurfer.tk:6969","udp://tracker.leechers-paradise.org:6969","udp://zer0day.ch:1337"],"infoHash":"b9db10be5bab1226fbe708b8989706ea0836e786","infoHashBuffer":{"type":"Buffer","data":[185,219,16,190,91,171,18,38,251,231,8,184,152,151,6,234,8,54,231,134]},"name":"WildOnCam 17 08 02 Marica Hase And Natasha Starr XXX 480p MP4-T","announce":["udp://exodus.desync.com:6969","udp://open.demonii.com:1337","udp://tracker.coppersurfer.tk:6969","udp://tracker.leechers-paradise.org:6969","udp://zer0day.ch:1337"],"urlList":[]}}