{"title":"FTVGirls 17 06 23 Kaylie The Benefits Of Flexibility XXX XviD S","magnet":"magnet:?xt=urn:btih:e5447beeaab3ba30bc658d340bca32f7c30dcf26&dn=FTVGirls+17+06+23+Kaylie+The+Benefits+Of+Flexibility+XXX+XviD+S&tr=udp%3A%2F%2Ftracker.leechers-paradise.org%3A6969&tr=udp%3A%2F%2Fzer0day.ch%3A1337&tr=udp%3A%2F%2Fopen.demonii.com%3A1337&tr=udp%3A%2F%2Ftracker.coppersurfer.tk%3A6969&tr=udp%3A%2F%2Fexodus.desync.com%3A6969","uploader":"PornXXX","categoryP":"porn","categoryS":"movie_clips","size":"739467850","seeders":"19","leechers":"20","description":"FTVGirls 17 06 23 Kaylie The Benefits Of Flexibility XXX XviD SD\n\nScreenshots:\n <a href=\"\nhttp://imagerar.com/img-594ca52dd6b4c.html\" rel=\"nofollow\" target=\"_NEW\">\nhttp://imagerar.com/img-594ca52dd6b4c.html</a>\n <a href=\"\nhttp://imagerar.com/img-594ca52dd131e.html\" rel=\"nofollow\" target=\"_NEW\">\nhttp://imagerar.com/img-594ca52dd131e.html</a>\n <a href=\"\nhttp://imagerar.com/img-594ca52dc28b1.html\" rel=\"nofollow\" target=\"_NEW\">\nhttp://imagerar.com/img-594ca52dc28b1.html</a>\n <a href=\"\nhttp://imagerar.com/img-594ca52b205fb.html\" rel=\"nofollow\" target=\"_NEW\">\nhttp://imagerar.com/img-594ca52b205fb.html</a>","last_updated":"2017-06-23T12:04:47.614Z","parsed":{"xt":"urn:btih:e5447beeaab3ba30bc658d340bca32f7c30dcf26","dn":"FTVGirls 17 06 23 Kaylie The Benefits Of Flexibility XXX XviD S","tr":["udp://exodus.desync.com:6969","udp://open.demonii.com:1337","udp://tracker.coppersurfer.tk:6969","udp://tracker.leechers-paradise.org:6969","udp://zer0day.ch:1337"],"infoHash":"e5447beeaab3ba30bc658d340bca32f7c30dcf26","infoHashBuffer":{"type":"Buffer","data":[229,68,123,238,170,179,186,48,188,101,141,52,11,202,50,247,195,13,207,38]},"name":"FTVGirls 17 06 23 Kaylie The Benefits Of Flexibility XXX XviD S","announce":["udp://exodus.desync.com:6969","udp://open.demonii.com:1337","udp://tracker.coppersurfer.tk:6969","udp://tracker.leechers-paradise.org:6969","udp://zer0day.ch:1337"],"urlList":[]}}