{"title":"Sasha Rose - Hot, Sticky, and Sweaty: Teens Pussy ","magnet":"magnet:?xt=urn:btih:f495624800843da7cdcdca3d9876a60a5043f33e&dn=Sasha+Rose+-+Hot%2C+Sticky%2C+and+Sweaty%3A+Teens+Pussy+&tr=udp%3A%2F%2Ftracker.leechers-paradise.org%3A6969&tr=udp%3A%2F%2Fzer0day.ch%3A1337&tr=udp%3A%2F%2Fopen.demonii.com%3A1337&tr=udp%3A%2F%2Ftracker.coppersurfer.tk%3A6969&tr=udp%3A%2F%2Fexodus.desync.com%3A6969","uploader":"adderiyk","categoryP":"porn","categoryS":"hd___movies","size":"891534092","seeders":"0","leechers":"0","description":" <a href=\"\nhttp://imgsalem.com/img-5945083b194a3.html\" rel=\"nofollow\" target=\"_NEW\">\nhttp://imgsalem.com/img-5945083b194a3.html</a> <a href=\"\nhttp://imgsalem.com/img-5945083b1ad44.html\" rel=\"nofollow\" target=\"_NEW\">\nhttp://imgsalem.com/img-5945083b1ad44.html</a>","last_updated":"2017-06-17T12:00:26.104Z","parsed":{"xt":"urn:btih:f495624800843da7cdcdca3d9876a60a5043f33e","dn":"Sasha Rose - Hot, Sticky, and Sweaty: Teens Pussy ","tr":["udp://exodus.desync.com:6969","udp://open.demonii.com:1337","udp://tracker.coppersurfer.tk:6969","udp://tracker.leechers-paradise.org:6969","udp://zer0day.ch:1337"],"infoHash":"f495624800843da7cdcdca3d9876a60a5043f33e","infoHashBuffer":{"type":"Buffer","data":[244,149,98,72,0,132,61,167,205,205,202,61,152,118,166,10,80,67,243,62]},"name":"Sasha Rose - Hot, Sticky, and Sweaty: Teens Pussy ","announce":["udp://exodus.desync.com:6969","udp://open.demonii.com:1337","udp://tracker.coppersurfer.tk:6969","udp://tracker.leechers-paradise.org:6969","udp://zer0day.ch:1337"],"urlList":[]}}