{"title":"Texas.Flip.and.Move.S06E08.Elevator.Barn.Build.WEB-DL.x264-JIVE","magnet":"magnet:?xt=urn:btih:f63299015656b71611865f012949ced89993c27d&dn=Texas.Flip.and.Move.S06E08.Elevator.Barn.Build.WEB-DL.x264-JIVE&tr=udp%3A%2F%2Ftracker.leechers-paradise.org%3A6969&tr=udp%3A%2F%2Fzer0day.ch%3A1337&tr=udp%3A%2F%2Fopen.demonii.com%3A1337&tr=udp%3A%2F%2Ftracker.coppersurfer.tk%3A6969&tr=udp%3A%2F%2Fexodus.desync.com%3A6969","uploader":"TvTeam","categoryP":"video","categoryS":"tv_shows","size":"423358151","seeders":"18","leechers":"10","description":"Torrent from:\r\n~~~~~~~~~~~~~~~~~~~~~~~~~~~~~\r\n <a href=\"\nhttps://torrenting.me\" rel=\"nofollow\" target=\"_NEW\">\nhttps://torrenting.me</a>\r\n\r\n~~~~~~~~~~~~~~~~~~~~~~~~~~~~~\r\n\r\nJoin us and become part of the BIG family! Yarrrrrrrrrrrrrr!!!","last_updated":"2017-06-13T12:03:32.333Z","parsed":{"xt":"urn:btih:f63299015656b71611865f012949ced89993c27d","dn":"Texas.Flip.and.Move.S06E08.Elevator.Barn.Build.WEB-DL.x264-JIVE","tr":["udp://exodus.desync.com:6969","udp://open.demonii.com:1337","udp://tracker.coppersurfer.tk:6969","udp://tracker.leechers-paradise.org:6969","udp://zer0day.ch:1337"],"infoHash":"f63299015656b71611865f012949ced89993c27d","infoHashBuffer":{"type":"Buffer","data":[246,50,153,1,86,86,183,22,17,134,95,1,41,73,206,216,153,147,194,125]},"name":"Texas.Flip.and.Move.S06E08.Elevator.Barn.Build.WEB-DL.x264-JIVE","announce":["udp://exodus.desync.com:6969","udp://open.demonii.com:1337","udp://tracker.coppersurfer.tk:6969","udp://tracker.leechers-paradise.org:6969","udp://zer0day.ch:1337"],"urlList":[]}}